solokit/__init__.py
solokit/__version__.py
solokit/cli.py
solokit/adopt/__init__.py
solokit/adopt/backup.py
solokit/adopt/doc_appender.py
solokit/adopt/merge_strategies.py
solokit/adopt/orchestrator.py
solokit/adopt/project_detector.py
solokit/commands/__init__.py
solokit/commands/config.py
solokit/commands/doctor.py
solokit/commands/help.py
solokit/commands/version.py
solokit/core/__init__.py
solokit/core/argparse_helpers.py
solokit/core/cache.py
solokit/core/cli_prompts.py
solokit/core/command_runner.py
solokit/core/config.py
solokit/core/config_validator.py
solokit/core/constants.py
solokit/core/error_formatter.py
solokit/core/error_handlers.py
solokit/core/exceptions.py
solokit/core/file_ops.py
solokit/core/logging_config.py
solokit/core/output.py
solokit/core/performance.py
solokit/core/protocols.py
solokit/core/system_utils.py
solokit/core/types.py
solokit/deployment/__init__.py
solokit/deployment/executor.py
solokit/git/__init__.py
solokit/git/integration.py
solokit/github/__init__.py
solokit/github/setup.py
solokit/init/__init__.py
solokit/init/claude_commands_installer.py
solokit/init/claude_md_generator.py
solokit/init/dependency_installer.py
solokit/init/docs_structure.py
solokit/init/env_generator.py
solokit/init/environment_validator.py
solokit/init/format_lint_fixer.py
solokit/init/git_hooks_installer.py
solokit/init/git_setup.py
solokit/init/gitignore_updater.py
solokit/init/initial_commit.py
solokit/init/initial_scans.py
solokit/init/orchestrator.py
solokit/init/readme_generator.py
solokit/init/session_structure.py
solokit/init/template_installer.py
solokit/learning/__init__.py
solokit/learning/archiver.py
solokit/learning/categorizer.py
solokit/learning/curator.py
solokit/learning/extractor.py
solokit/learning/reporter.py
solokit/learning/repository.py
solokit/learning/similarity.py
solokit/learning/validator.py
solokit/project/__init__.py
solokit/project/adopt.py
solokit/project/init.py
solokit/project/stack.py
solokit/project/sync_plugin.py
solokit-0.3.0.dist-info/licenses/LICENSE
solokit-0.3.0.dist-info/METADATA
solokit-0.3.0.dist-info/WHEEL
solokit-0.3.0.dist-info/entry_points.txt
solokit-0.3.0.dist-info/top_level.txt
solokit-0.3.0.dist-info/RECORD
