Metadata-Version: 2.4
Name: solokit
Version: 0.3.0
Summary: Solokit - Structured Solo Development with AI and Quality Automation
Author: Solokit Contributors
License: MIT
Project-URL: Homepage, https://github.com/ankushdixit/solokit
Project-URL: Documentation, https://github.com/ankushdixit/solokit/blob/main/README.md
Project-URL: Repository, https://github.com/ankushdixit/solokit
Project-URL: Issues, https://github.com/ankushdixit/solokit/issues
Project-URL: Changelog, https://github.com/ankushdixit/solokit/blob/main/CHANGELOG.md
Keywords: solo-development,ai-native,workflow,quality-automation,productivity,ai-assistant,claude-code
Classifier: Development Status :: 4 - Beta
Classifier: Intended Audience :: Developers
Classifier: License :: OSI Approved :: MIT License
Classifier: Programming Language :: Python :: 3
Classifier: Programming Language :: Python :: 3.11
Classifier: Programming Language :: Python :: 3.12
Classifier: Programming Language :: Python :: 3.13
Classifier: Topic :: Software Development :: Libraries :: Python Modules
Classifier: Topic :: Software Development :: Quality Assurance
Classifier: Topic :: Software Development :: Testing
Requires-Python: >=3.11
License-File: LICENSE
Requires-Dist: PyYAML<7.0.0,>=6.0.0
Requires-Dist: questionary<3.0.0,>=2.0.0
Requires-Dist: jsonschema<5.0.0,>=4.20.0
Requires-Dist: tomli-w<2.0.0,>=1.0.0
Provides-Extra: test
Requires-Dist: pytest<8.0.0,>=7.4.3; extra == "test"
Requires-Dist: pytest-cov<5.0.0,>=4.1.0; extra == "test"
Provides-Extra: quality
Requires-Dist: ruff<0.2.0,>=0.1.6; extra == "quality"
Requires-Dist: bandit<2.0.0,>=1.7.5; extra == "quality"
Requires-Dist: safety<3.0.0,>=2.3.5; extra == "quality"
Requires-Dist: mypy<2.0.0,>=1.8.0; extra == "quality"
Requires-Dist: types-PyYAML<7.0.0,>=6.0.0; extra == "quality"
Provides-Extra: viz
Requires-Dist: graphviz<0.21.0,>=0.20.1; extra == "viz"
Provides-Extra: dev
Requires-Dist: solokit[quality,test,viz]; extra == "dev"
Dynamic: license-file
